{
      "results": [
            {
                  "distance": 501,
                  "location": {
                        "address": "8990 Sherbrooke Rue E",
                        "country": "CA",
                        "cross_street": "",
                        "formatted_address": "8990 Sherbrooke Rue E, Montr\u00e9al QC H1L 1C9",
                        "locality": "Montreal",
                        "postcode": "H1L 1C9",
                        "region": "QC"
                  },
                  "name": "Boulangerie MariePain",
                  "popularity": 0.9910933951551855,
                  "price": 1,
                  "rating": 7.9
            },
            {
                  "distance": 385,
                  "location": {
                        "address": "8670 Sherbrooke Rue E",
                        "country": "CA",
                        "cross_street": "",
                        "formatted_address": "8670 Sherbrooke Rue E, Montr\u00e9al QC H1L 1B9",
                        "locality": "Montreal",
                        "postcode": "H1L 1B9",
                        "region": "QC"
                  },
                  "name": "Le Grill Barroso",
                  "popularity": 0.8786194171082513,
                  "price": 2,
                  "rating": 7.4
            },
            {
                  "distance": 369,
                  "location": {
                        "address": "5272 Sherbrooke Rue O",
                        "country": "CA",
                        "cross_street": "",
                        "formatted_address": "5272 Sherbrooke Rue O, Montr\u00e9al QC H4A 1T9",
                        "locality": "Montreal",
                        "postcode": "H4A 1T9",
                        "region": "QC"
                  },
                  "name": "KFC",
                  "popularity": 0.9679929977289932,
                  "price": 1,
                  "rating": 6.4
            },
            {
                  "distance": 710,
                  "location": {
                        "address": "9325 Sherbrooke St E",
                        "country": "CA",
                        "cross_street": "",
                        "formatted_address": "9325 Sherbrooke St E, Montr\u00e9al QC H1L 6P2",
                        "locality": "Montreal",
                        "postcode": "H1L 6P2",
                        "region": "QC"
                  },
                  "name": "Subway",
                  "popularity": 0.9523325132475398,
                  "price": 1,
                  "rating": 6.4,
                  "store_id": "26312"
            },
            {
                  "distance": 310,
                  "location": {
                        "address": "9198 Sherbrooke Rue E",
                        "country": "CA",
                        "cross_street": "",
                        "formatted_address": "9198 Sherbrooke Rue E, Montr\u00e9al QC H1L 1E5",
                        "locality": "Montreal",
                        "postcode": "H1L 1E5",
                        "region": "QC"
                  },
                  "name": "Caf\u00e9 Sunset",
                  "popularity": 0.5367264383043149,
                  "price": 1
            },
            {
                  "distance": 363,
                  "location": {
                        "address": "8655 Sherbrooke Rue E",
                        "country": "CA",
                        "cross_street": "",
                        "formatted_address": "8655 Sherbrooke Rue E, Montr\u00e9al QC H1L 1B8",
                        "locality": "Montreal",
                        "postcode": "H1L 1B8",
                        "region": "QC"
                  },
                  "name": "Broadway Pizzeria",
                  "popularity": 0.8714278955336866,
                  "price": 1
            },
            {
                  "distance": 396,
                  "location": {
                        "address": "8604 Sherbrooke Rue E",
                        "country": "CA",
                        "cross_street": "",
                        "formatted_address": "8604 Sherbrooke Rue E, Montr\u00e9al QC",
                        "locality": "Montreal",
                        "region": "QC"
                  },
                  "name": "Double Pizza",
                  "popularity": 0.826528198334595,
                  "price": 1
            },
            {
                  "distance": 401,
                  "location": {
                        "address": "8660 Sherbrooke Rue E",
                        "country": "CA",
                        "formatted_address": "8660 Sherbrooke Rue E, Montr\u00e9al QC H1L 1B7",
                        "locality": "Montreal",
                        "postcode": "H1L 1B7",
                        "region": "QC"
                  },
                  "name": "Restaurant la Belle Province",
                  "popularity": 0.9033047880393641,
                  "price": 1
            },
            {
                  "distance": 413,
                  "location": {
                        "address": "8604 Sherbrooke Rue E",
                        "country": "CA",
                        "cross_street": "",
                        "formatted_address": "8604 Sherbrooke Rue E, Montr\u00e9al QC H1L 1B7",
                        "locality": "Montreal",
                        "postcode": "H1L 1B7",
                        "region": "QC"
                  },
                  "name": "Pizza Hut",
                  "popularity": 0.9349096328538986,
                  "price": 1,
                  "store_id": "R47401"
            },
            {
                  "distance": 480,
                  "location": {
                        "address": "9005 Sherbrooke Rue E",
                        "country": "CA",
                        "cross_street": "",
                        "formatted_address": "9005 Sherbrooke Rue E, Montr\u00e9al QC H1L 1C8",
                        "locality": "Montreal",
                        "postcode": "H1L 1C8",
                        "region": "QC"
                  },
                  "name": "Brasserie Sherbrooke",
                  "popularity": 0.8930616010598031,
                  "price": 2
            },
            {
                  "distance": 593,
                  "location": {
                        "address": "9100 Sherbrooke Rue E",
                        "country": "CA",
                        "cross_street": "",
                        "formatted_address": "9100 Sherbrooke Rue E, Montreal QC",
                        "locality": "Montreal",
                        "region": "QC"
                  },
                  "name": "Restaurant le Petit Quebec",
                  "popularity": 0.9605412566237699,
                  "price": 1
            },
            {
                  "distance": 676,
                  "location": {
                        "address": "9194 Sherbrooke Rue E",
                        "country": "CA",
                        "cross_street": "",
                        "formatted_address": "9194 Sherbrooke Rue E, Montr\u00e9al QC H1L 1E5",
                        "locality": "Montreal",
                        "postcode": "H1L 1E5",
                        "region": "QC"
                  },
                  "name": "Cari Masala",
                  "popularity": 0.8693934519303558,
                  "price": 2
            },
            {
                  "distance": 972,
                  "location": {
                        "address": "9546 Sherbrooke Rue E",
                        "country": "CA",
                        "cross_street": "",
                        "formatted_address": "9546 Sherbrooke Rue E, Montr\u00e9al QC H1L 1E8",
                        "locality": "Montreal",
                        "postcode": "H1L 1E8",
                        "region": "QC"
                  },
                  "name": "Caf\u00e9 Bar Gypsy",
                  "popularity": 0.8859173921271764,
                  "price": 2
            },
            {
                  "distance": 2950,
                  "location": {
                        "address": "9020 Sherbrooke Rue E",
                        "country": "CA",
                        "cross_street": "Desmarteau",
                        "formatted_address": "9020 Sherbrooke Rue E (Desmarteau), Montr\u00e9al QC H1L 1C9",
                        "locality": "Montreal",
                        "postcode": "H1L 1C9",
                        "region": "QC"
                  },
                  "name": "Pizza 2 Pour 1",
                  "popularity": 0.14915310370931112,
                  "price": 1
            },
            {
                  "distance": 333,
                  "location": {
                        "address": "8715 Est Sherbrooke",
                        "country": "CA",
                        "formatted_address": "8715 Est Sherbrooke, Montreal QC H1K 1C1",
                        "locality": "Montreal",
                        "postcode": "H1K 1C1",
                        "region": "QC"
                  },
                  "name": "Fusion Viet Asie"
            },
            {
                  "distance": 349,
                  "location": {
                        "address": "8655 Sherbrooke Rue E",
                        "country": "CA",
                        "formatted_address": "8655 Sherbrooke Rue E, Montreal QC H1L 1B8",
                        "locality": "Montreal",
                        "postcode": "H1L 1B8",
                        "region": "QC"
                  },
                  "name": "Scores - Montr\u00e9al"
            },
            {
                  "distance": 476,
                  "location": {
                        "address": "9005 Sherbrooke Rue E",
                        "country": "CA",
                        "formatted_address": "9005 Sherbrooke Rue E, Montreal QC H1L 1C8",
                        "locality": "Montreal",
                        "postcode": "H1L 1C8",
                        "region": "QC"
                  },
                  "name": "Bar Salon Sherbrooke Est Enr"
            },
            {
                  "distance": 500,
                  "location": {
                        "address": "5020 Saint-Donat Rue",
                        "country": "CA",
                        "formatted_address": "5020 Saint-Donat Rue, Montreal QC H1K 3N8",
                        "locality": "Montreal",
                        "postcode": "H1K 3N8",
                        "region": "QC"
                  },
                  "name": "Lakay"
            },
            {
                  "distance": 603,
                  "location": {
                        "address": "9100 Sherbrooke Rue E",
                        "country": "CA",
                        "formatted_address": "9100 Sherbrooke Rue E, Montreal QC H1L 1E3",
                        "locality": "Montreal",
                        "postcode": "H1L 1E3",
                        "region": "QC"
                  },
                  "name": "P'tit Quebec"
            },
            {
                  "distance": 859,
                  "location": {
                        "address": "2864 des Ormeaux Rue",
                        "country": "CA",
                        "formatted_address": "2864 des Ormeaux Rue, Montreal QC H1L 4X8",
                        "locality": "Montreal",
                        "postcode": "H1L 4X8",
                        "region": "QC"
                  },
                  "name": "Restaurant le des Ormeaux"
            },
            {
                  "distance": 870,
                  "location": {
                        "address": "9191 rue de Marseille",
                        "country": "CA",
                        "formatted_address": "9191 rue de Marseille, Montreal QC H1L 1T2",
                        "locality": "Montreal",
                        "postcode": "H1L 1T2",
                        "region": "QC"
                  },
                  "name": "Le Gout Secret des Caraibes"
            },
            {
                  "distance": 901,
                  "location": {
                        "address": "9191 rue de Marseille",
                        "country": "CA",
                        "formatted_address": "9191 rue de Marseille, Montreal QC H1L 1T2",
                        "locality": "Montreal",
                        "postcode": "H1L 1T2",
                        "region": "QC"
                  },
                  "name": "Restaurant le Quartier"
            }
      ],
      "context": {
            "geo_bounds": {
                  "circle": {
                        "center": {
                              "latitude": 45.60590173,
                              "longitude": -73.53436947
                        },
                        "radius": 1000
                  }
            }
      }
}