{
      "businesses": [
            {
                  "id": "lWCJWq3Y06ld1NU5cBarvA",
                  "alias": "l-hamburger-montr\u00e9al-3",
                  "name": "L\u2019Hamburger",
                  "image_url": "https://s3-media3.fl.yelpcdn.com/bphoto/Vkasf_K1cVlDsA7Zmb5NGg/o.jpg",
                  "is_closed": false,
                  "url": "https://www.yelp.com/biz/l-hamburger-montr%C3%A9al-3?adjust_creative=DDOLgNZllWHhOhr3P5a1xQ&utm_campaign=yelp_api_v3&utm_medium=api_v3_business_search&utm_source=DDOLgNZllWHhOhr3P5a1xQ",
                  "review_count": 8,
                  "categories": [
                        {
                              "alias": "burgers",
                              "title": "Burgers"
                        },
                        {
                              "alias": "juicebars",
                              "title": "Juice Bars & Smoothies"
                        }
                  ],
                  "rating": 5.0,
                  "coordinates": {
                        "latitude": 45.53851,
                        "longitude": -73.60603
                  },
                  "transactions": [],
                  "location": {
                        "address1": "933 Rue Saint-Zotique",
                        "address2": null,
                        "address3": "",
                        "city": "Montreal",
                        "zip_code": "H2S 1M9",
                        "country": "CA",
                        "state": "QC",
                        "display_address": [
                              "933 Rue Saint-Zotique",
                              "Montreal, QC H2S 1M9",
                              "Canada"
                        ]
                  },
                  "phone": "+14383759400",
                  "display_phone": "+1 438-375-9400",
                  "distance": 946.5348757302295
            },
            {
                  "id": "MMnGeUrHR6q2zllksmJQqw",
                  "alias": "bibiko-montr\u00e9al",
                  "name": "Bibiko",
                  "image_url": "https://s3-media1.fl.yelpcdn.com/bphoto/j_FL6ThV5V0UDDoCANlsCg/o.jpg",
                  "is_closed": false,
                  "url": "https://www.yelp.com/biz/bibiko-montr%C3%A9al?adjust_creative=DDOLgNZllWHhOhr3P5a1xQ&utm_campaign=yelp_api_v3&utm_medium=api_v3_business_search&utm_source=DDOLgNZllWHhOhr3P5a1xQ",
                  "review_count": 8,
                  "categories": [
                        {
                              "alias": "korean",
                              "title": "Korean"
                        }
                  ],
                  "rating": 5.0,
                  "coordinates": {
                        "latitude": 45.52639,
                        "longitude": -73.59886
                  },
                  "transactions": [],
                  "location": {
                        "address1": "31 Rue Saint Viateur E",
                        "address2": "",
                        "address3": null,
                        "city": "Montreal",
                        "zip_code": "H2T 1A5",
                        "country": "CA",
                        "state": "QC",
                        "display_address": [
                              "31 Rue Saint Viateur E",
                              "Montreal, QC H2T 1A5",
                              "Canada"
                        ]
                  },
                  "phone": "+15142702424",
                  "display_phone": "+1 514-270-2424",
                  "distance": 897.2427876880797
            },
            {
                  "id": "bIZbtbOhD404RJGvfGKc8w",
                  "alias": "pizza-bouquet-montr\u00e9al",
                  "name": "Pizza Bouquet",
                  "image_url": "https://s3-media1.fl.yelpcdn.com/bphoto/7GaxPN5fJWNkFZHnP7KbYQ/o.jpg",
                  "is_closed": false,
                  "url": "https://www.yelp.com/biz/pizza-bouquet-montr%C3%A9al?adjust_creative=DDOLgNZllWHhOhr3P5a1xQ&utm_campaign=yelp_api_v3&utm_medium=api_v3_business_search&utm_source=DDOLgNZllWHhOhr3P5a1xQ",
                  "review_count": 14,
                  "categories": [
                        {
                              "alias": "pizza",
                              "title": "Pizza"
                        }
                  ],
                  "rating": 5.0,
                  "coordinates": {
                        "latitude": 45.530835990936275,
                        "longitude": -73.60811021045075
                  },
                  "transactions": [],
                  "location": {
                        "address1": "45 Rue Beaubien E",
                        "address2": "",
                        "address3": null,
                        "city": "Montreal",
                        "zip_code": "H2S 1P8",
                        "country": "CA",
                        "state": "QC",
                        "display_address": [
                              "45 Rue Beaubien E",
                              "Montreal, QC H2S 1P8",
                              "Canada"
                        ]
                  },
                  "phone": "+14383206069",
                  "display_phone": "+1 438-320-6069",
                  "distance": 1044.5740822482214
            },
            {
                  "id": "R_nf8ZVc_TreNyMN_vLMjA",
                  "alias": "sports-de-combats-montr\u00e9al",
                  "name": "Sports de Combats",
                  "image_url": "https://s3-media4.fl.yelpcdn.com/bphoto/3FFeQXHOX_kmL-SdrKU7nA/o.jpg",
                  "is_closed": false,
                  "url": "https://www.yelp.com/biz/sports-de-combats-montr%C3%A9al?adjust_creative=DDOLgNZllWHhOhr3P5a1xQ&utm_campaign=yelp_api_v3&utm_medium=api_v3_business_search&utm_source=DDOLgNZllWHhOhr3P5a1xQ",
                  "review_count": 18,
                  "categories": [
                        {
                              "alias": "recreation",
                              "title": "Recreation Centers"
                        },
                        {
                              "alias": "eventplanning",
                              "title": "Party & Event Planning"
                        },
                        {
                              "alias": "teambuilding",
                              "title": "Team Building Activities"
                        }
                  ],
                  "rating": 5.0,
                  "coordinates": {
                        "latitude": 45.5263029,
                        "longitude": -73.5952509
                  },
                  "transactions": [],
                  "location": {
                        "address1": "5335 Avenue Casgrain",
                        "address2": null,
                        "address3": "",
                        "city": "Montreal",
                        "zip_code": "H2T 1X4",
                        "country": "CA",
                        "state": "QC",
                        "display_address": [
                              "5335 Avenue Casgrain",
                              "Montreal, QC H2T 1X4",
                              "Canada"
                        ]
                  },
                  "phone": "+15146133894",
                  "display_phone": "+1 514-613-3894",
                  "distance": 867.1306768216253
            },
            {
                  "id": "9wJNXm3L-N1lEeIKwrTNgg",
                  "alias": "fromagerie-maitre-affineur-maitre-corbeau-montr\u00e9al-4",
                  "name": "Fromagerie Maitre Affineur Maitre Corbeau",
                  "image_url": "https://s3-media2.fl.yelpcdn.com/bphoto/au6nj_qNPiW9FPDQQYqybg/o.jpg",
                  "is_closed": false,
                  "url": "https://www.yelp.com/biz/fromagerie-maitre-affineur-maitre-corbeau-montr%C3%A9al-4?adjust_creative=DDOLgNZllWHhOhr3P5a1xQ&utm_campaign=yelp_api_v3&utm_medium=api_v3_business_search&utm_source=DDOLgNZllWHhOhr3P5a1xQ",
                  "review_count": 8,
                  "categories": [
                        {
                              "alias": "delis",
                              "title": "Delis"
                        },
                        {
                              "alias": "cheese",
                              "title": "Cheese Shops"
                        }
                  ],
                  "rating": 5.0,
                  "coordinates": {
                        "latitude": 45.53316,
                        "longitude": -73.58425
                  },
                  "transactions": [],
                  "location": {
                        "address1": "5101 Rue Chambord",
                        "address2": "",
                        "address3": "",
                        "city": "Montreal",
                        "zip_code": "H2J 3N4",
                        "country": "CA",
                        "state": "QC",
                        "display_address": [
                              "5101 Rue Chambord",
                              "Montreal, QC H2J 3N4",
                              "Canada"
                        ]
                  },
                  "phone": "+15145283293",
                  "display_phone": "+1 514-528-3293",
                  "distance": 883.8038367190396
            },
            {
                  "id": "c7B5OHwqAJSu8QZQdLQ-Mg",
                  "alias": "la-belle-tonki-montr\u00e9al",
                  "name": "La Belle Tonki",
                  "image_url": "https://s3-media2.fl.yelpcdn.com/bphoto/8LZ2mxblCSG9XZBdezYQeQ/o.jpg",
                  "is_closed": false,
                  "url": "https://www.yelp.com/biz/la-belle-tonki-montr%C3%A9al?adjust_creative=DDOLgNZllWHhOhr3P5a1xQ&utm_campaign=yelp_api_v3&utm_medium=api_v3_business_search&utm_source=DDOLgNZllWHhOhr3P5a1xQ",
                  "review_count": 10,
                  "categories": [
                        {
                              "alias": "asianfusion",
                              "title": "Asian Fusion"
                        },
                        {
                              "alias": "vietnamese",
                              "title": "Vietnamese"
                        }
                  ],
                  "rating": 4.5,
                  "coordinates": {
                        "latitude": 45.54066,
                        "longitude": -73.599463
                  },
                  "transactions": [],
                  "location": {
                        "address1": "1335 Rue Beaubien E",
                        "address2": null,
                        "address3": "",
                        "city": "Montreal",
                        "zip_code": "H2G 1K7",
                        "country": "CA",
                        "state": "QC",
                        "display_address": [
                              "1335 Rue Beaubien E",
                              "Montreal, QC H2G 1K7",
                              "Canada"
                        ]
                  },
                  "phone": "+15144190660",
                  "display_phone": "+1 514-419-0660",
                  "distance": 791.1464301344666
            },
            {
                  "id": "08R3xSHVEFtvn7oxLu54sQ",
                  "alias": "caifan-tacos-bar-montr\u00e9al-5",
                  "name": "Caifan Tacos Bar",
                  "image_url": "https://s3-media1.fl.yelpcdn.com/bphoto/Jca1K47spl8pFT4gCAispQ/o.jpg",
                  "is_closed": false,
                  "url": "https://www.yelp.com/biz/caifan-tacos-bar-montr%C3%A9al-5?adjust_creative=DDOLgNZllWHhOhr3P5a1xQ&utm_campaign=yelp_api_v3&utm_medium=api_v3_business_search&utm_source=DDOLgNZllWHhOhr3P5a1xQ",
                  "review_count": 16,
                  "categories": [
                        {
                              "alias": "mexican",
                              "title": "Mexican"
                        }
                  ],
                  "rating": 4.5,
                  "coordinates": {
                        "latitude": 45.53119,
                        "longitude": -73.60795
                  },
                  "transactions": [],
                  "price": "$$",
                  "location": {
                        "address1": "67 Rue Beaubien E",
                        "address2": "",
                        "address3": null,
                        "city": "Montreal",
                        "zip_code": "H2S 1R1",
                        "country": "CA",
                        "state": "QC",
                        "display_address": [
                              "67 Rue Beaubien E",
                              "Montreal, QC H2S 1R1",
                              "Canada"
                        ]
                  },
                  "phone": "+15149038585",
                  "display_phone": "+1 514-903-8585",
                  "distance": 1006.5338893174978
            },
            {
                  "id": "K1ala_vciG1UETtJECYsvg",
                  "alias": "caf\u00e9-pista-montr\u00e9al-2",
                  "name": "Caf\u00e9 Pista",
                  "image_url": "https://s3-media1.fl.yelpcdn.com/bphoto/EX23gK6MireqsNO4cIhCow/o.jpg",
                  "is_closed": false,
                  "url": "https://www.yelp.com/biz/caf%C3%A9-pista-montr%C3%A9al-2?adjust_creative=DDOLgNZllWHhOhr3P5a1xQ&utm_campaign=yelp_api_v3&utm_medium=api_v3_business_search&utm_source=DDOLgNZllWHhOhr3P5a1xQ",
                  "review_count": 36,
                  "categories": [
                        {
                              "alias": "breakfast_brunch",
                              "title": "Breakfast & Brunch"
                        },
                        {
                              "alias": "cafes",
                              "title": "Cafes"
                        }
                  ],
                  "rating": 4.5,
                  "coordinates": {
                        "latitude": 45.534791,
                        "longitude": -73.60432
                  },
                  "transactions": [],
                  "price": "$",
                  "location": {
                        "address1": "500 Rue Beaubien East",
                        "address2": "",
                        "address3": "",
                        "city": "Montreal",
                        "zip_code": "H2S 1S5",
                        "country": "CA",
                        "state": "QC",
                        "display_address": [
                              "500 Rue Beaubien East",
                              "Montreal, QC H2S 1S5",
                              "Canada"
                        ]
                  },
                  "phone": "+15149038257",
                  "display_phone": "+1 514-903-8257",
                  "distance": 688.6126588878467
            },
            {
                  "id": "IShLrIQtlbW6WuWnhPWsLw",
                  "alias": "pastel-rita-montr\u00e9al",
                  "name": "Pastel Rita",
                  "image_url": "https://s3-media3.fl.yelpcdn.com/bphoto/oKOz-cCTWnegY3SXNt1vYA/o.jpg",
                  "is_closed": false,
                  "url": "https://www.yelp.com/biz/pastel-rita-montr%C3%A9al?adjust_creative=DDOLgNZllWHhOhr3P5a1xQ&utm_campaign=yelp_api_v3&utm_medium=api_v3_business_search&utm_source=DDOLgNZllWHhOhr3P5a1xQ",
                  "review_count": 22,
                  "categories": [
                        {
                              "alias": "cafes",
                              "title": "Cafes"
                        }
                  ],
                  "rating": 4.5,
                  "coordinates": {
                        "latitude": 45.52723,
                        "longitude": -73.60137
                  },
                  "transactions": [],
                  "price": "$",
                  "location": {
                        "address1": "5761 Boulevard St-Laurent",
                        "address2": "",
                        "address3": null,
                        "city": "Montreal",
                        "zip_code": "H2T 1S9",
                        "country": "CA",
                        "state": "QC",
                        "display_address": [
                              "5761 Boulevard St-Laurent",
                              "Montreal, QC H2T 1S9",
                              "Canada"
                        ]
                  },
                  "phone": "+15143980213",
                  "display_phone": "+1 514-398-0213",
                  "distance": 902.4596285770667
            },
            {
                  "id": "Eh4xDNioChV54KPLs5nmSw",
                  "alias": "caf\u00e9-district-montr\u00e9al-2",
                  "name": "Caf\u00e9 District",
                  "image_url": "https://s3-media2.fl.yelpcdn.com/bphoto/lmviwVHi7AfkOwPm7p8NDg/o.jpg",
                  "is_closed": false,
                  "url": "https://www.yelp.com/biz/caf%C3%A9-district-montr%C3%A9al-2?adjust_creative=DDOLgNZllWHhOhr3P5a1xQ&utm_campaign=yelp_api_v3&utm_medium=api_v3_business_search&utm_source=DDOLgNZllWHhOhr3P5a1xQ",
                  "review_count": 8,
                  "categories": [
                        {
                              "alias": "coffee",
                              "title": "Coffee & Tea"
                        },
                        {
                              "alias": "sandwiches",
                              "title": "Sandwiches"
                        }
                  ],
                  "rating": 4.5,
                  "coordinates": {
                        "latitude": 45.5270743,
                        "longitude": -73.59805180000001
                  },
                  "transactions": [],
                  "price": "$",
                  "location": {
                        "address1": "83 Saint-Viateur Est",
                        "address2": "",
                        "address3": "",
                        "city": "Montreal",
                        "zip_code": "H2T 1A7",
                        "country": "CA",
                        "state": "QC",
                        "display_address": [
                              "83 Saint-Viateur Est",
                              "Montreal, QC H2T 1A7",
                              "Canada"
                        ]
                  },
                  "phone": "+15142708931",
                  "display_phone": "+1 514-270-8931",
                  "distance": 805.3094829624686
            },
            {
                  "id": "H464UiJ5c7q5dAJ14h731A",
                  "alias": "gus-montr\u00e9al",
                  "name": "Gus",
                  "image_url": "https://s3-media1.fl.yelpcdn.com/bphoto/qCpzAjAgRLcC1RHkHCQ6-A/o.jpg",
                  "is_closed": false,
                  "url": "https://www.yelp.com/biz/gus-montr%C3%A9al?adjust_creative=DDOLgNZllWHhOhr3P5a1xQ&utm_campaign=yelp_api_v3&utm_medium=api_v3_business_search&utm_source=DDOLgNZllWHhOhr3P5a1xQ",
                  "review_count": 92,
                  "categories": [
                        {
                              "alias": "seafood",
                              "title": "Seafood"
                        },
                        {
                              "alias": "steak",
                              "title": "Steakhouses"
                        }
                  ],
                  "rating": 4.5,
                  "coordinates": {
                        "latitude": 45.5306384,
                        "longitude": -73.6080747
                  },
                  "transactions": [],
                  "price": "$$$",
                  "location": {
                        "address1": "38 Rue Beaubien E",
                        "address2": "",
                        "address3": "",
                        "city": "Montreal",
                        "zip_code": "H2S 1P8",
                        "country": "CA",
                        "state": "QC",
                        "display_address": [
                              "38 Rue Beaubien E",
                              "Montreal, QC H2S 1P8",
                              "Canada"
                        ]
                  },
                  "phone": "+15147222175",
                  "display_phone": "+1 514-722-2175",
                  "distance": 1049.8341739605908
            },
            {
                  "id": "X180L6_G0PnuXuVyr9sNUA",
                  "alias": "groz\u00e9pa-montr\u00e9al",
                  "name": "Groz\u00e9pa",
                  "image_url": "https://s3-media1.fl.yelpcdn.com/bphoto/WnCRBfzSjE8NCSp09sTEfg/o.jpg",
                  "is_closed": false,
                  "url": "https://www.yelp.com/biz/groz%C3%A9pa-montr%C3%A9al?adjust_creative=DDOLgNZllWHhOhr3P5a1xQ&utm_campaign=yelp_api_v3&utm_medium=api_v3_business_search&utm_source=DDOLgNZllWHhOhr3P5a1xQ",
                  "review_count": 14,
                  "categories": [
                        {
                              "alias": "bars",
                              "title": "Bars"
                        },
                        {
                              "alias": "italian",
                              "title": "Italian"
                        },
                        {
                              "alias": "pizza",
                              "title": "Pizza"
                        }
                  ],
                  "rating": 4.5,
                  "coordinates": {
                        "latitude": 45.5406389190071,
                        "longitude": -73.590926020582
                  },
                  "transactions": [],
                  "location": {
                        "address1": "5885 Avenue Papineau",
                        "address2": "",
                        "address3": null,
                        "city": "Montreal",
                        "zip_code": "H2G 2W5",
                        "country": "CA",
                        "state": "QC",
                        "display_address": [
                              "5885 Avenue Papineau",
                              "Montreal, QC H2G 2W5",
                              "Canada"
                        ]
                  },
                  "phone": "+15143030335",
                  "display_phone": "+1 514-303-0335",
                  "distance": 810.9981558040274
            },
            {
                  "id": "lgS1QFmVFPVbTOKRxTcW4g",
                  "alias": "mazbi-montr\u00e9al",
                  "name": "Mazbi",
                  "image_url": "https://s3-media1.fl.yelpcdn.com/bphoto/n77A9Tgl3o9_K7Nw-oXXNg/o.jpg",
                  "is_closed": false,
                  "url": "https://www.yelp.com/biz/mazbi-montr%C3%A9al?adjust_creative=DDOLgNZllWHhOhr3P5a1xQ&utm_campaign=yelp_api_v3&utm_medium=api_v3_business_search&utm_source=DDOLgNZllWHhOhr3P5a1xQ",
                  "review_count": 23,
                  "categories": [
                        {
                              "alias": "mideastern",
                              "title": "Middle Eastern"
                        }
                  ],
                  "rating": 4.5,
                  "coordinates": {
                        "latitude": 45.52512,
                        "longitude": -73.58486
                  },
                  "transactions": [],
                  "location": {
                        "address1": "4669 Rue Saint-Denis",
                        "address2": "",
                        "address3": null,
                        "city": "Montreal",
                        "zip_code": "H2J 2L5",
                        "country": "CA",
                        "state": "QC",
                        "display_address": [
                              "4669 Rue Saint-Denis",
                              "Montreal, QC H2J 2L5",
                              "Canada"
                        ]
                  },
                  "phone": "+15143756181",
                  "display_phone": "+1 514-375-6181",
                  "distance": 1299.257813231568
            },
            {
                  "id": "OoAOASAURjvuao3glnS0bw",
                  "alias": "santiago-montr\u00e9al",
                  "name": "Santiago",
                  "image_url": "https://s3-media2.fl.yelpcdn.com/bphoto/e19eltOuV5y6mJgcZ0uAQA/o.jpg",
                  "is_closed": false,
                  "url": "https://www.yelp.com/biz/santiago-montr%C3%A9al?adjust_creative=DDOLgNZllWHhOhr3P5a1xQ&utm_campaign=yelp_api_v3&utm_medium=api_v3_business_search&utm_source=DDOLgNZllWHhOhr3P5a1xQ",
                  "review_count": 4,
                  "categories": [
                        {
                              "alias": "caribbean",
                              "title": "Caribbean"
                        },
                        {
                              "alias": "international",
                              "title": "International"
                        }
                  ],
                  "rating": 5.0,
                  "coordinates": {
                        "latitude": 45.54088,
                        "longitude": -73.59827
                  },
                  "transactions": [],
                  "location": {
                        "address1": "1376 Rue Beaubien E",
                        "address2": null,
                        "address3": "",
                        "city": "Montreal",
                        "zip_code": "H2G 1K9",
                        "country": "CA",
                        "state": "QC",
                        "display_address": [
                              "1376 Rue Beaubien E",
                              "Montreal, QC H2G 1K9",
                              "Canada"
                        ]
                  },
                  "phone": "+14382893944",
                  "display_phone": "+1 438-289-3944",
                  "distance": 790.1050512547957
            },
            {
                  "id": "zCSX6Q3HSJ7RxHM5zhmTBw",
                  "alias": "montr\u00e9al-plaza-montr\u00e9al-2",
                  "name": "Montr\u00e9al Plaza",
                  "image_url": "https://s3-media1.fl.yelpcdn.com/bphoto/6KnO49B4VxJJRW8qAIhjYA/o.jpg",
                  "is_closed": false,
                  "url": "https://www.yelp.com/biz/montr%C3%A9al-plaza-montr%C3%A9al-2?adjust_creative=DDOLgNZllWHhOhr3P5a1xQ&utm_campaign=yelp_api_v3&utm_medium=api_v3_business_search&utm_source=DDOLgNZllWHhOhr3P5a1xQ",
                  "review_count": 101,
                  "categories": [
                        {
                              "alias": "newcanadian",
                              "title": "Canadian (New)"
                        }
                  ],
                  "rating": 4.5,
                  "coordinates": {
                        "latitude": 45.534836,
                        "longitude": -73.600521
                  },
                  "transactions": [],
                  "price": "$$$$",
                  "location": {
                        "address1": "6230 Rue Saint-Hubert",
                        "address2": "",
                        "address3": "",
                        "city": "Montreal",
                        "zip_code": "H2S 2M2",
                        "country": "CA",
                        "state": "QC",
                        "display_address": [
                              "6230 Rue Saint-Hubert",
                              "Montreal, QC H2S 2M2",
                              "Canada"
                        ]
                  },
                  "phone": "+15149036230",
                  "display_phone": "+1 514-903-6230",
                  "distance": 396.95172327243495
            },
            {
                  "id": "6wZIRMkNY3XVF3rSoMLHNQ",
                  "alias": "le-super-qualit\u00e9-montr\u00e9al",
                  "name": "Le Super Qualit\u00e9",
                  "image_url": "https://s3-media3.fl.yelpcdn.com/bphoto/dfox_Tm8C51SvHTHR_y8ew/o.jpg",
                  "is_closed": false,
                  "url": "https://www.yelp.com/biz/le-super-qualit%C3%A9-montr%C3%A9al?adjust_creative=DDOLgNZllWHhOhr3P5a1xQ&utm_campaign=yelp_api_v3&utm_medium=api_v3_business_search&utm_source=DDOLgNZllWHhOhr3P5a1xQ",
                  "review_count": 36,
                  "categories": [
                        {
                              "alias": "indpak",
                              "title": "Indian"
                        }
                  ],
                  "rating": 4.5,
                  "coordinates": {
                        "latitude": 45.5420266,
                        "longitude": -73.60769449631381
                  },
                  "transactions": [],
                  "price": "$$",
                  "location": {
                        "address1": "1211 Rue B\u00e9langer",
                        "address2": "",
                        "address3": null,
                        "city": "Montreal",
                        "zip_code": "H2S 1H7",
                        "country": "CA",
                        "state": "QC",
                        "display_address": [
                              "1211 Rue B\u00e9langer",
                              "Montreal, QC H2S 1H7",
                              "Canada"
                        ]
                  },
                  "phone": "+15143980184",
                  "display_phone": "+1 514-398-0184",
                  "distance": 1293.858424570156
            },
            {
                  "id": "zktCQRlDtF6XmOpqKBz1mA",
                  "alias": "le-vestiaire-montr\u00e9al",
                  "name": "Le Vestiaire",
                  "image_url": "https://s3-media3.fl.yelpcdn.com/bphoto/RY1E_RBjmM1Vu0q5RaC_eQ/o.jpg",
                  "is_closed": false,
                  "url": "https://www.yelp.com/biz/le-vestiaire-montr%C3%A9al?adjust_creative=DDOLgNZllWHhOhr3P5a1xQ&utm_campaign=yelp_api_v3&utm_medium=api_v3_business_search&utm_source=DDOLgNZllWHhOhr3P5a1xQ",
                  "review_count": 28,
                  "categories": [
                        {
                              "alias": "pubs",
                              "title": "Pubs"
                        },
                        {
                              "alias": "brasseries",
                              "title": "Brasseries"
                        },
                        {
                              "alias": "karaoke",
                              "title": "Karaoke"
                        }
                  ],
                  "rating": 4.5,
                  "coordinates": {
                        "latitude": 45.53701,
                        "longitude": -73.60569
                  },
                  "transactions": [],
                  "price": "$$",
                  "location": {
                        "address1": "6634 Rue Saint-Hubert",
                        "address2": "",
                        "address3": "",
                        "city": "Montreal",
                        "zip_code": "H2S 2M3",
                        "country": "CA",
                        "state": "QC",
                        "display_address": [
                              "6634 Rue Saint-Hubert",
                              "Montreal, QC H2S 2M3",
                              "Canada"
                        ]
                  },
                  "phone": "+15145643823",
                  "display_phone": "+1 514-564-3823",
                  "distance": 852.9815393137973
            },
            {
                  "id": "BqcybcdZJ8EPSql3fwqZ2g",
                  "alias": "darna-bistroquet-montr\u00e9al-3",
                  "name": "Darna Bistroquet",
                  "image_url": "https://s3-media4.fl.yelpcdn.com/bphoto/18M4dCGAPwENbu0Z_pUn1Q/o.jpg",
                  "is_closed": false,
                  "url": "https://www.yelp.com/biz/darna-bistroquet-montr%C3%A9al-3?adjust_creative=DDOLgNZllWHhOhr3P5a1xQ&utm_campaign=yelp_api_v3&utm_medium=api_v3_business_search&utm_source=DDOLgNZllWHhOhr3P5a1xQ",
                  "review_count": 13,
                  "categories": [
                        {
                              "alias": "bistros",
                              "title": "Bistros"
                        }
                  ],
                  "rating": 4.5,
                  "coordinates": {
                        "latitude": 45.53815,
                        "longitude": -73.60102
                  },
                  "transactions": [],
                  "location": {
                        "address1": "1106 Rue Beaubien E",
                        "address2": null,
                        "address3": "",
                        "city": "Montreal",
                        "zip_code": "H2S 1T5",
                        "country": "CA",
                        "state": "QC",
                        "display_address": [
                              "1106 Rue Beaubien E",
                              "Montreal, QC H2S 1T5",
                              "Canada"
                        ]
                  },
                  "phone": "+15142731106",
                  "display_phone": "+1 514-273-1106",
                  "distance": 610.2770262456444
            },
            {
                  "id": "tAj-0ZPUATzLHS0KHzXFBQ",
                  "alias": "la-raclette-montr\u00e9al",
                  "name": "La Raclette",
                  "image_url": "https://s3-media3.fl.yelpcdn.com/bphoto/zenF0IqXHfQ9paRTFFhd8w/o.jpg",
                  "is_closed": false,
                  "url": "https://www.yelp.com/biz/la-raclette-montr%C3%A9al?adjust_creative=DDOLgNZllWHhOhr3P5a1xQ&utm_campaign=yelp_api_v3&utm_medium=api_v3_business_search&utm_source=DDOLgNZllWHhOhr3P5a1xQ",
                  "review_count": 50,
                  "categories": [
                        {
                              "alias": "fondue",
                              "title": "Fondue"
                        },
                        {
                              "alias": "french",
                              "title": "French"
                        }
                  ],
                  "rating": 4.5,
                  "coordinates": {
                        "latitude": 45.5295503804062,
                        "longitude": -73.5827571103087
                  },
                  "transactions": [],
                  "price": "$$$",
                  "location": {
                        "address1": "1059 Rue Gilford",
                        "address2": "",
                        "address3": "",
                        "city": "Montreal",
                        "zip_code": "H2J 1P7",
                        "country": "CA",
                        "state": "QC",
                        "display_address": [
                              "1059 Rue Gilford",
                              "Montreal, QC H2J 1P7",
                              "Canada"
                        ]
                  },
                  "phone": "+15145248118",
                  "display_phone": "+1 514-524-8118",
                  "distance": 1116.404749051386
            },
            {
                  "id": "eKyi29EJvNYcx5-rxkSyqQ",
                  "alias": "bod\u00e9g\u00e2t-montr\u00e9al",
                  "name": "Bo'D\u00e9g\u00e2t",
                  "image_url": "https://s3-media3.fl.yelpcdn.com/bphoto/nK7Wkj7a9rp2d8l3twnvhQ/o.jpg",
                  "is_closed": false,
                  "url": "https://www.yelp.com/biz/bod%C3%A9g%C3%A2t-montr%C3%A9al?adjust_creative=DDOLgNZllWHhOhr3P5a1xQ&utm_campaign=yelp_api_v3&utm_medium=api_v3_business_search&utm_source=DDOLgNZllWHhOhr3P5a1xQ",
                  "review_count": 7,
                  "categories": [
                        {
                              "alias": "spanish",
                              "title": "Spanish"
                        },
                        {
                              "alias": "tapas",
                              "title": "Tapas Bars"
                        }
                  ],
                  "rating": 4.5,
                  "coordinates": {
                        "latitude": 45.54097,
                        "longitude": -73.59836
                  },
                  "transactions": [],
                  "location": {
                        "address1": "1392 Rue Beaubien E",
                        "address2": null,
                        "address3": "",
                        "city": "Montreal",
                        "zip_code": "H2G 1K9",
                        "country": "CA",
                        "state": "QC",
                        "display_address": [
                              "1392 Rue Beaubien E",
                              "Montreal, QC H2G 1K9",
                              "Canada"
                        ]
                  },
                  "phone": "+15144958104",
                  "display_phone": "+1 514-495-8104",
                  "distance": 781.6437248179722
            }
      ],
      "total": 227,
      "region": {
            "center": {
                  "longitude": -73.59553456,
                  "latitude": 45.53409867
            }
      }
}